LICENSE
MANIFEST.in
README.rst
setup.py
codepadr/__init__.py
codepadr/cli.py
codepadr.egg-info/PKG-INFO
codepadr.egg-info/SOURCES.txt
codepadr.egg-info/dependency_links.txt
codepadr.egg-info/entry_points.txt
codepadr.egg-info/requires.txt
codepadr.egg-info/top_level.txt