Metadata-Version: 1.0
Name: codepadr
Version: 0.9
Summary: A tool for uploading to codepad.org
Home-page: https://github.com/autoplectic/codepadr
Author: Ryan James
Author-email: rgjames@ucdavis.edu
License: LITL
Platform: UNKNOWN
Classifier: Development Status :: 4 - Beta
Classifier: Environment :: Console
Classifier: Operating System :: OS Independent
Classifier: Programming Language :: Python
